gsql/GSQL.toml
gsql/__init__.py
gsql/__main__.py
gsql/btree.py
gsql/cli.py
gsql/database.py
gsql/exceptions.py
gsql/executor.py
gsql/exp.py
gsql/functions.py
gsql/index.py
gsql/parser.py
gsql/storage.py
gsql/test.py
gsql/cli/__init__.py
gsql/cli/colors.py
gsql/cli/formatter.py
gsql/config/defaults.yaml
gsql/functions/user_functions.py
gsql/functions/__pycache__/__init__.py
gsql/ma_base.db_data/meta/users.json
gsql/ma_base.db_data/tables/users.json
gsql/nlp/patterns.json
gsql/nlp/translator.py
gsql/storage/__init__.py
gsql/storage/exceptions.py
gsql/storage/sqlite_storage.py
gsql/tests/function.py
gsql/tests/test_nlp.py
gsql-3.10.0.dist-info/licenses/LICENSE
gsql-3.10.0.dist-info/METADATA
gsql-3.10.0.dist-info/WHEEL
gsql-3.10.0.dist-info/entry_points.txt
gsql-3.10.0.dist-info/top_level.txt
gsql-3.10.0.dist-info/RECORD
