Metadata-Version: 2.4
Name: gsql
Version: 3.10.0
Summary: Complete SQL Database System in Python with AI Integration
Home-page: https://github.com/gopu-inc/gsql
Author: Gopu Inc.
Author-email: ceoseshell@gmail.com
Maintainer: GSQL Maintainers
Maintainer-email: maintainers@gopu-inc.com
License: MIT
Project-URL: Homepage, https://github.com/gopu-inc/gsql
Project-URL: Documentation, https://gsql.readthedocs.io
Project-URL: Source Code, https://github.com/gopu-inc/gsql
Project-URL: Bug Tracker, https://github.com/gopu-inc/gsql/issues
Project-URL: Changelog, https://github.com/gopu-inc/gsql/releases
Project-URL: Discussions, https://github.com/gopu-inc/gsql/discussions
Project-URL: Docker Hub, https://hub.docker.com/r/ceoseshell/gsql
Project-URL: PyPI, https://pypi.org/project/gsql/
Project-URL: Anaconda, https://anaconda.org/ceoseshell/gsql
Keywords: sql,database,sqlite,python,ai,nlp,machine-learning,data-science,analytics,cli,rest-api,docker,kubernetes
Platform: any
Classifier: Development Status :: 5 - Production/Stable
Classifier: Intended Audience :: Developers
Classifier: Topic :: Database
Classifier: Topic :: Database :: Database Engines/Servers
Classifier: License :: OSI Approved :: MIT License
Classifier: Programming Language :: Python :: 3
Classifier: Programming Language :: Python :: 3.8
Classifier: Programming Language :: Python :: 3.9
Classifier: Programming Language :: Python :: 3.10
Classifier: Programming Language :: Python :: 3.11
Classifier: Programming Language :: Python :: 3.12
Classifier: Operating System :: OS Independent
Requires-Python: >=3.8
License-File: LICENSE
Requires-Dist: click
Requires-Dist: colorama
Requires-Dist: prompt-toolkit
Requires-Dist: rich
Requires-Dist: numpy
Requires-Dist: nltk
Requires-Dist: psutil
Requires-Dist: typing-extensions
Requires-Dist: cryptography
Provides-Extra: dev
Requires-Dist: pytest>=7.0.0; extra == "dev"
Requires-Dist: pytest-cov>=4.0.0; extra == "dev"
Requires-Dist: black>=23.0.0; extra == "dev"
Requires-Dist: flake8>=6.0.0; extra == "dev"
Requires-Dist: mypy>=1.0.0; extra == "dev"
Requires-Dist: isort>=5.12.0; extra == "dev"
Provides-Extra: test
Requires-Dist: pytest>=7.0.0; extra == "test"
Requires-Dist: pytest-cov>=4.0.0; extra == "test"
Requires-Dist: pytest-mock>=3.10.0; extra == "test"
Provides-Extra: docs
Requires-Dist: sphinx>=7.0.0; extra == "docs"
Requires-Dist: sphinx-rtd-theme>=1.3.0; extra == "docs"
Provides-Extra: all
Requires-Dist: pandas>=1.5.0; extra == "all"
Requires-Dist: numpy>=1.24.0; extra == "all"
Requires-Dist: nltk>=3.8.0; extra == "all"
Requires-Dist: spacy>=3.6.0; extra == "all"
Requires-Dist: fastapi>=0.100.0; extra == "all"
Requires-Dist: uvicorn>=0.23.0; extra == "all"
Dynamic: author
Dynamic: author-email
Dynamic: classifier
Dynamic: description
Dynamic: description-content-type
Dynamic: home-page
Dynamic: keywords
Dynamic: license
Dynamic: license-file
Dynamic: maintainer
Dynamic: maintainer-email
Dynamic: platform
Dynamic: project-url
Dynamic: provides-extra
Dynamic: requires-dist
Dynamic: requires-python
Dynamic: summary
